tests/__init__.py
tests/benchmark.py
tests/test_connection.py
tests/test_crypto_connection.py
tests/test_heap.py
tests/test_packet.py
tests/test_rudp.py
txrudp/__init__.py
txrudp/connection.py
txrudp/constants.py
txrudp/crypto_connection.py
txrudp/heap.py
txrudp/packet.py
txrudp/packet_pb2.py
txrudp/rudp.py
txrudp-0.4.1.dist-info/DESCRIPTION.rst
txrudp-0.4.1.dist-info/METADATA
txrudp-0.4.1.dist-info/RECORD
txrudp-0.4.1.dist-info/WHEEL
txrudp-0.4.1.dist-info/metadata.json
txrudp-0.4.1.dist-info/top_level.txt
