Metadata-Version: 2.0
Name: txrudp
Version: 0.4.1
Summary: A Twisted extension implementing RUDP
Home-page: https://github.com/OpenBazaar/txrudp
Author: Nikolaos Korasidis
Author-email: renelvon@gmail.com
License: MIT
Keywords: rudp twisted reliable
Platform: UNKNOWN
Classifier: Development Status :: 4 - Beta
Classifier: Framework :: Twisted
Classifier: Intended Audience :: Developers
Classifier: License :: OSI Approved :: MIT License
Classifier: Operating System :: POSIX :: Linux
Classifier: Programming Language :: Python :: 2
Classifier: Programming Language :: Python :: 2.7
Classifier: Programming Language :: Python :: Implementation :: CPython
Classifier: Topic :: System :: Networking
Requires-Dist: enum34
Requires-Dist: protobuf
Requires-Dist: twisted
Provides-Extra: crypto
Requires-Dist: pynacl; extra == 'crypto'
